blipfuzzytest/__init__.py
blipfuzzytest/blipfuzzytest.py
blipfuzzytest-0.0.2.dist-info/LICENSE.txt
blipfuzzytest-0.0.2.dist-info/METADATA
blipfuzzytest-0.0.2.dist-info/WHEEL
blipfuzzytest-0.0.2.dist-info/RECORD
